textwrap3.py
textwrap3-0.9.1.dist-info/DESCRIPTION.rst
textwrap3-0.9.1.dist-info/METADATA
textwrap3-0.9.1.dist-info/RECORD
textwrap3-0.9.1.dist-info/WHEEL
textwrap3-0.9.1.dist-info/metadata.json
textwrap3-0.9.1.dist-info/top_level.txt
